docs/conf.py
scripts/check_performance.py
scripts/update_changelog_metrics.py
tests/__init__.py
tests/test_smoke.py
tests/core/__init__.py
tests/core/ml/__init__.py
tests/core/ml/test_constructor.py
tests/feature_selection/__init__.py
tests/metrics/__init__.py
tests/preprocessing/__init__.py
tests/quality/__init__.py
tests/utils/__init__.py
xplainable/__init__.py
xplainable/_dependencies.py
xplainable/_version.py
xplainable/config.py
xplainable/callbacks/__init__.py
xplainable/callbacks/optimisation.py
xplainable/core/__init__.py
xplainable/core/models.py
xplainable/core/ml/__init__.py
xplainable/core/ml/_base_model.py
xplainable/core/ml/_constructor.py
xplainable/core/ml/_constructor_parameters.py
xplainable/core/ml/classification.py
xplainable/core/ml/regression.py
xplainable/core/ml/surrogate.py
xplainable/core/nlp/__init__.py
xplainable/core/nlp/feature_extraction.py
xplainable/core/optimisation/__init__.py
xplainable/core/optimisation/bayesian.py
xplainable/core/optimisation/genetic.py
xplainable/core/optimisation/layers.py
xplainable/core/optimisation/nlp.py
xplainable/core/optimisation/targeting.py
xplainable/feature_selection/__init__.py
xplainable/feature_selection/classification.py
xplainable/feature_selection/graph.py
xplainable/gpt/__init__.py
xplainable/gpt/report.py
xplainable/gui/__init__.py
xplainable/gui/components/__init__.py
xplainable/gui/components/bars.py
xplainable/gui/components/cards.py
xplainable/gui/components/connectivity.py
xplainable/gui/components/header.py
xplainable/gui/components/pipelines.py
xplainable/gui/components/tables.py
xplainable/gui/gradio/__init__.py
xplainable/gui/gradio/fine_tuning.py
xplainable/gui/screens/__init__.py
xplainable/gui/screens/classifier.py
xplainable/gui/screens/evaluate.py
xplainable/gui/screens/loader.py
xplainable/gui/screens/preprocessor.py
xplainable/gui/screens/regressor.py
xplainable/gui/screens/save.py
xplainable/gui/screens/scenario.py
xplainable/metrics/__init__.py
xplainable-1.3.1.dist-info/licenses/LICENSE
xplainable-1.3.1.dist-info/METADATA
xplainable-1.3.1.dist-info/WHEEL
xplainable-1.3.1.dist-info/top_level.txt
xplainable-1.3.1.dist-info/RECORD
