Metadata-Version: 2.4
Name: xplainable
Version: 1.3.1
Summary: Real-time explainable machine learning for business optimisation
Author-email: xplainable pty ltd <contact@xplainable.io>
License:                     GNU AFFERO GENERAL PUBLIC LICENSE
Classifier: Programming Language :: Python :: 3.8
Classifier: Programming Language :: Python :: 3.9
Classifier: Programming Language :: Python :: 3.10
Classifier: Programming Language :: Python :: 3.11
Classifier: Operating System :: OS Independent
Requires-Python: >=3.8
License-File: LICENSE
Requires-Dist: drawsvg>=2.1.1
Requires-Dist: hyperopt>=0.2.7
Requires-Dist: ipywidgets>=8.0.5
Requires-Dist: matplotlib>=3.4.2
Requires-Dist: numba>=0.57.0
Requires-Dist: numpy>=2.0.0
Requires-Dist: pandas>=2.2.3
Requires-Dist: pyperclip>=1.8.2
Requires-Dist: requests
Requires-Dist: scikit-learn>=1.3.0
Requires-Dist: scipy>=1.6.2
Requires-Dist: seaborn>=0.11.1
Requires-Dist: traitlets>=5.5.0
Requires-Dist: urllib3>=1.26.5
Requires-Dist: psutil>=5.9.4
Requires-Dist: joblib>=1.2.0
Requires-Dist: jupyter-client==7.3.2
Requires-Dist: altair>=5.0.1
Requires-Dist: networkx>=2.8.0
Requires-Dist: tqdm>=4.62.3
Requires-Dist: plotly>=5.1.0
Requires-Dist: packaging
Requires-Dist: sphinx_rtd_theme
Provides-Extra: gui
Requires-Dist: jupyter-client==7.3.2; extra == "gui"
Requires-Dist: ipywidgets>=8.0.5; extra == "gui"
Requires-Dist: matplotlib>=3.4.2; extra == "gui"
Requires-Dist: seaborn>=0.11.1; extra == "gui"
Requires-Dist: traitlets>=5.5.0; extra == "gui"
Requires-Dist: drawsvg>=2.1.1; extra == "gui"
Requires-Dist: gradio>=3.35.0; extra == "gui"
Provides-Extra: plotting
Requires-Dist: matplotlib>=3.4.2; extra == "plotting"
Requires-Dist: seaborn>=0.11.1; extra == "plotting"
Requires-Dist: altair>=5.0.1; extra == "plotting"
Requires-Dist: plotly>=5.1.0; extra == "plotting"
Dynamic: license-file
